cuda_downloader.py
cuda_switch.py
cuda_switch-1.0.0.dist-info/licenses/LICENSE
cuda_switch-1.0.0.dist-info/METADATA
cuda_switch-1.0.0.dist-info/WHEEL
cuda_switch-1.0.0.dist-info/entry_points.txt
cuda_switch-1.0.0.dist-info/top_level.txt
cuda_switch-1.0.0.dist-info/RECORD
