Metadata-Version: 2.4
Name: cuda-switch
Version: 1.0.0
Summary: A tool for managing multiple CUDA versions on macOS
Home-page: https://github.com/yourusername/cuda-switch
Author: Jason Wang
Author-email: Jason Wang <your-email@example.com>
License: MIT
Project-URL: Homepage, https://github.com/yourusername/cuda-switch
Project-URL: Bug Reports, https://github.com/yourusername/cuda-switch/issues
Project-URL: Source Code, https://github.com/yourusername/cuda-switch
Keywords: cuda,nvidia,gpu,development,macos
Classifier: Development Status :: 4 - Beta
Classifier: Intended Audience :: Developers
Classifier: Topic :: Software Development :: Build Tools
Classifier: License :: OSI Approved :: MIT License
Classifier: Programming Language :: Python :: 3
Classifier: Programming Language :: Python :: 3.7
Classifier: Programming Language :: Python :: 3.8
Classifier: Programming Language :: Python :: 3.9
Classifier: Programming Language :: Python :: 3.10
Classifier: Programming Language :: Python :: 3.11
Classifier: Operating System :: MacOS
Requires-Python: >=3.7
License-File: LICENSE
Requires-Dist: requests>=2.25.0
Requires-Dist: beautifulsoup4>=4.9.0
Requires-Dist: lxml>=4.6.0
Dynamic: author
Dynamic: home-page
Dynamic: license-file
Dynamic: requires-python
